Metadata-Version: 2.0
Name: lemming
Version: 0.1.1
Summary: Python3 project layout generator
Home-page: https://lemming.xnode.co.za
Author: Paul Stevens
Author-email: ps@xnode.co.za
License: UNKNOWN
Platform: UNKNOWN
Classifier: Development Status :: 4 - Beta
Classifier: Programming Language :: Python
Classifier: Programming Language :: Python :: 3
Classifier: Programming Language :: Python :: 3.5
Classifier: Programming Language :: Python :: 3.6
Classifier: Environment :: Console
Classifier: Intended Audience :: Developers
Classifier: Intended Audience :: System Administrators
Classifier: License :: OSI Approved :: MIT License
Classifier: Topic :: Software Development
Classifier: Topic :: Terminals
Classifier: Topic :: Utilities
Requires-Dist: Jinja2 (>=2.10)
Requires-Dist: ruamel.yaml (>=0.15.35)
